{
  "schema_version": "1.0",
  "source_file": "Bank Good Credit Loan.pptx.json",
  "total_entries": 1,
  "entries": [
    {
      "id": "76997baa-a90e-44a1-ac11-db2ee4180d1b",
      "type": "general",
      "title": "[\n    {\n        \"type\": \"Title\",\n        \"element_...",
      "content": "[\n    {\n        \"type\": \"Title\",\n        \"element_id\": \"0405351ac64213c7b1e40e31aff7d21b\",\n        \"metadata\": {\n            \"filename\": \"Bank Good Credit Loan.pptx\",\n            \"file_directory\": \"tmpdocs\",\n            \"last_modified\": \"2023-11-02T15:16:14\",\n            \"filetype\": \"application/vnd.openxmlformats-officedocument.presentationml.presentation\",\n            \"category_depth\": 1,\n            \"languages\": [\n                \"eng\"\n            ],\n            \"page_number\": 1\n        },\n        \"text\": \"Bank Good Credit \"\n    },\n    {\n        \"type\": \"NarrativeText\",\n        \"element_id\": \"214987ebee9fd615365185fb3d692253\",\n        \"metadata\": {\n            \"filename\": \"Bank Good Credit Loan.pptx\",\n            \"file_directory\": \"tmpdocs\",\n            \"last_modified\": \"2023-11-02T15:16:14\",\n            \"filetype\": \"application/vnd.openxmlformats-officedocument.presentationml.presentation\",\n            \"parent_id\": \"0405351ac64213c7b1e40e31aff7d21b\",\n            \"category_depth\": 0,\n            \"languages\": [\n                \"eng\"\n            ],\n            \"page_number\": 1\n        },\n        \"text\": \"Accredited with IABAC\\u2122\"\n    },\n    {\n        \"type\": \"Title\",\n        \"element_id\": \"fc3d53b1d173c5c72205914ea331b052\",\n        \"metadata\": {\n            \"filename\": \"Bank Good Credit Loan.pptx\",\n            \"file_directory\": \"tmpdocs\",\n            \"last_modified\": \"2023-11-02T15:16:14\",\n            \"filetype\": \"application/vnd.openxmlformats-officedocument.presentationml.presentation\",\n            \"category_depth\": 1,\n            \"languages\": [\n                \"eng\"\n            ],\n            \"page_number\": 1\n        },\n        \"text\": \"( International Association of Business Analytics Certifications)`\"\n    },\n    {\n        \"type\": \"Title\",\n        \"element_id\": \"b952b3e6d0e34020f1f48b5d9243d0a4\",\n        \"metadata\": {\n            \"filename\": \"Bank Good Credit Loan.pptx\",\n            \"file_directory\": \"tmpdocs\",\n            \"last_modified\": \"2023-11-02T15:16:14\",\n            \"filetype\": \"application/vnd.openxmlformats-officedocument.presentationml.presentation\",\n            \"category_depth\": 1,\n            \"languages\": [\n                \"eng\"\n            ],\n            \"page_number\": 1\n        },\n        \"text\": \"\\u00a9 DataMites\\u2122. All Rights Reserved | www.datamites.com\"\n    },\n    {\n        \"type\": \"Title\",\n        \"element_id\": \"2dc308bd8d3a5c745dfacc3bdccd81db\",\n        \"metadata\": {\n            \"filename\": \"Bank Good Credit Loan.pptx\",\n            \"file_directory\": \"tmpdocs\",\n            \"last_modified\": \"2023-11-02T15:16:14\",\n            \"filetype\": \"application/vnd.openxmlformats-officedocument.presentationml.presentation\",\n            \"category_depth\": 0,\n            \"languages\": [\n                \"eng\"\n            ],\n            \"page_number\": 2\n        },\n        \"text\": \"Objective & Background\"\n    },\n    {\n        \"type\": \"ListItem\",\n        \"element_id\": \"5a0a7e2a14285297ff3752656cb6df44\",\n        \"metadata\": {\n            \"filename\": \"Bank Good Credit Loan.pptx\",\n            \"file_directory\": \"tmpdocs\",\n            \"last_modified\": \"2023-11-02T15:16:14\",\n            \"filetype\": \"application/vnd.openxmlformats-officedocument.presentationml.presentation\",\n            \"parent_id\": \"2dc308bd8d3a5c745dfacc3bdccd81db\",\n            \"category_depth\": 1,\n            \"languages\": [\n                \"eng\"\n            ],\n            \"page_number\": 2\n        },\n        \"text\": \"Classify credit card customers as good / bad, based on information from internal and external sources. \"\n    },\n    {\n        \"type\": \"ListItem\",\n        \"element_id\": \"5eb6ec96e6a3493c1ae56747ae457b7f\",\n        \"metadata\": {\n            \"filename\": \"Bank Good Credit Loan.pptx\",\n            \"file_directory\": \"tmpdocs\",\n            \"last_modified\": \"2023-11-02T15:16:14\",\n            \"filetype\": \"application/vnd.openxmlformats-officedocument.presentationml.presentation\",\n            \"parent_id\": \"2dc308bd8d3a5c745dfacc3bdccd81db\",\n            \"category_depth\": 1,\n            \"languages\": [\n                \"eng\"\n            ],\n            \"page_number\": 2\n        },\n        \"text\": \"Data provided\"\n    },\n    {\n        \"type\": \"ListItem\",\n        \"element_id\": \"adec2b6c75369165b1d87dccdfd2dab8\",\n        \"metadata\": {\n            \"filename\": \"Bank Good Credit Loan.pptx\",\n            \"file_directory\": \"tmpdocs\",\n            \"last_modified\": \"2023-11-02T15:16:14\",\n            \"filetype\": \"application/vnd.openxmlformats-officedocument.presentationml.presentation\",\n            \"parent_id\": \"5eb6ec96e6a3493c1ae56747ae457b7f\",\n            \"category_depth\": 2,\n            \"languages\": [\n                \"eng\"\n            ],\n            \"page_number\": 2\n        },\n        \"text\": \"Demographic: Base file of with credit card history details. Only one record for every customer.\"\n    },\n    {\n        \"type\": \"ListItem\",\n        \"element_id\": \"c26d6dc6982b7f42045f4ffee951f8e0\",\n        \"metadata\": {\n            \"filename\": \"Bank Good Credit Loan.pptx\",\n            \"file_directory\": \"tmpdocs\",\n            \"last_modified\": \"2023-11-02T15:16:14\",\n            \"filetype\": \"application/vnd.openxmlformats-officedocument.presentationml.presentation\",\n            \"parent_id\": \"5eb6ec96e6a3493c1ae56747ae457b7f\",\n            \"category_depth\": 2,\n            \"languages\": [\n                \"eng\"\n            ],\n            \"page_number\": 2\n        },\n        \"text\": \"Account: Contians data for various loans availed by the customer. Not related to credit card. Multiple records for every customer.\"\n    },\n    {\n        \"type\": \"ListItem\",\n        \"element_id\": \"be3fc5cb3da83e6c22d1906330ee9f96\",\n        \"metadata\": {\n            \"filename\": \"Bank Good Credit Loan.pptx\",\n            \"file_directory\": \"tmpdocs\",\n            \"last_modified\": \"2023-11-02T15:16:14\",\n            \"filetype\": \"application/vnd.openxmlformats-officedocument.presentationml.presentation\",\n            \"parent_id\": \"5eb6ec96e6a3493c1ae56747ae457b7f\",\n            \"category_depth\": 2,\n            \"languages\": [\n                \"eng\"\n            ],\n            \"page_number\": 2\n        },\n        \"text\": \"Enquiries: Enquired made by customers for different loan purposes. Multiple records for every customer.\\t\"\n    },\n    {\n        \"type\": \"Title\",\n        \"element_id\": \"b952b3e6d0e34020f1f48b5d9243d0a4\",\n        \"metadata\": {\n            \"filename\": \"Bank Good Credit Loan.pptx\",\n            \"file_directory\": \"tmpdocs\",\n            \"last_modified\": \"2023-11-02T15:16:14\",\n            \"filetype\": \"application/vnd.openxmlformats-officedocument.presentationml.presentation\",\n            \"parent_id\": \"2dc308bd8d3a5c745dfacc3bdccd81db\",\n            \"category_depth\": 1,\n            \"languages\": [\n                \"eng\"\n            ],\n            \"page_number\": 2\n        },\n        \"text\": \"\\u00a9 DataMites\\u2122. All Rights Reserved | www.datamites.com\"\n    },\n    {\n        \"type\": \"Title\",\n        \"element_id\": \"0072e6b934945d5ba08f9729e0084739\",\n        \"metadata\": {\n            \"filename\": \"Bank Good Credit Loan.pptx\",\n            \"file_directory\": \"tmpdocs\",\n            \"last_modified\": \"2023-11-02T15:16:14\",\n            \"filetype\": \"application/vnd.openxmlformats-officedocument.presentationml.presentation\",\n            \"category_depth\": 0,\n            \"languages\": [\n                \"eng\"\n            ],\n            \"page_number\": 3\n        },\n        \"text\": \"Design\"\n    },\n    {\n        \"type\": \"ListItem\",\n        \"element_id\": \"af14c0ecaaa7ac1d2bca5cdfbcc32ec7\",\n        \"metadata\": {\n            \"filename\": \"Bank Good Credit Loan.pptx\",\n            \"file_directory\": \"tmpdocs\",\n            \"last_modified\": \"2023-11-02T15:16:14\",\n            \"filetype\": \"application/vnd.openxmlformats-officedocument.presentationml.presentation\",\n            \"parent_id\": \"0072e6b934945d5ba08f9729e0084739\",\n            \"category_depth\": 0,\n            \"languages\": [\n                \"eng\"\n            ],\n            \"page_number\": 3\n        },\n        \"text\": \"Data to be downloaded using SQL queries.\"\n    },\n    {\n        \"type\": \"ListItem\",\n        \"element_id\": \"51d8e67259ab8a11d2fdfc5cb9bcf45e\",\n        \"metadata\": {\n            \"filename\": \"Bank Good Credit Loan.pptx\",\n            \"file_directory\": \"tmpdocs\",\n            \"last_modified\": \"2023-11-02T15:16:14\",\n            \"filetype\": \"application/vnd.openxmlformats-officedocument.presentationml.presentation\",\n            \"parent_id\": \"0072e6b934945d5ba08f9729e0084739\",\n            \"category_depth\": 0,\n            \"languages\": [\n                \"eng\"\n            ],\n            \"page_number\": 3\n        },\n        \"text\": \"Required information to be extracted from Account and Enquiry files and converted to one-to-one files.\"\n    },\n    {\n        \"type\": \"ListItem\",\n        \"element_id\": \"6165e3bc219556f6ec397adc7240386b\",\n        \"metadata\": {\n            \"filename\": \"Bank Good Credit Loan.pptx\",\n            \"file_directory\": \"tmpdocs\",\n            \"last_modified\": \"2023-11-02T15:16:14\",\n            \"filetype\": \"application/vnd.openxmlformats-officedocument.presentationml.presentation\",\n            \"parent_id\": \"0072e6b934945d5ba08f9729e0084739\",\n            \"category_depth\": 0,\n            \"languages\": [\n                \"eng\"\n            ],\n            \"page_number\": 3\n        },\n        \"text\": \"The columns from the two files should be merged with Demographic file using Left Join with \\u201ccustomer no\\u201d as key column, to create a final file. The final file should contain all the records in demographic and additional columns/features from Account and Enquiry files will get added to Demographic file.\"\n    },\n    {\n        \"type\": \"ListItem\",\n        \"element_id\": \"31930936fc3bad2175b05e324e9923e4\",\n        \"metadata\": {\n            \"filename\": \"Bank Good Credit Loan.pptx\",\n            \"file_directory\": \"tmpdocs\",\n            \"last_modified\": \"2023-11-02T15:16:14\",\n            \"filetype\": \"application/vnd.openxmlformats-officedocument.presentationml.presentation\",\n            \"parent_id\": \"0072e6b934945d5ba08f9729e0084739\",\n            \"category_depth\": 0,\n            \"languages\": [\n                \"eng\"\n            ],\n            \"page_number\": 3\n        },\n        \"text\": \"There will be many customers in account and enquiry file who will get left out. This is fine as we anyway don\\u2019t know their good/bad label for training purpose. \"\n    },\n    {\n        \"type\": \"Title\",\n        \"element_id\": \"b952b3e6d0e34020f1f48b5d9243d0a4\",\n        \"metadata\": {\n            \"filename\": \"Bank Good Credit Loan.pptx\",\n            \"file_directory\": \"tmpdocs\",\n            \"last_modified\": \"2023-11-02T15:16:14\",\n            \"filetype\": \"application/vnd.openxmlformats-officedocument.presentationml.presentation\",\n            \"parent_id\": \"0072e6b934945d5ba08f9729e0084739\",\n            \"category_depth\": 1,\n            \"languages\": [\n                \"eng\"\n            ],\n            \"page_number\": 3\n        },\n        \"text\": \"\\u00a9 DataMites\\u2122. All Rights Reserved | www.datamites.com\"\n    },\n    {\n        \"type\": \"Title\",\n        \"element_id\": \"ed83647ab77addbea9e4dca5f7d8f216\",\n        \"metadata\": {\n            \"filename\": \"Bank Good Credit Loan.pptx\",\n            \"file_directory\": \"tmpdocs\",\n            \"last_modified\": \"2023-11-02T15:16:14\",\n            \"filetype\": \"application/vnd.openxmlformats-officedocument.presentationml.presentation\",\n            \"category_depth\": 0,\n            \"languages\": [\n                \"eng\"\n            ],\n            \"page_number\": 4\n        },\n        \"text\": \"Analysis of Data\"\n    },\n    {\n        \"type\": \"ListItem\",\n        \"element_id\": \"d936f750c577a228ebabd9ed2cec9a70\",\n        \"metadata\": {\n            \"filename\": \"Bank Good Credit Loan.pptx\",\n            \"file_directory\": \"tmpdocs\",\n            \"last_modified\": \"2023-11-02T15:16:14\",\n            \"filetype\": \"application/vnd.openxmlformats-officedocument.presentationml.presentation\",\n            \"parent_id\": \"ed83647ab77addbea9e4dca5f7d8f216\",\n            \"category_depth\": 1,\n            \"languages\": [\n                \"eng\"\n            ],\n            \"page_number\": 4\n        },\n        \"text\": \"Show using Excel File\"\n    },\n    {\n        \"type\": \"Title\",\n        \"element_id\": \"b952b3e6d0e34020f1f48b5d9243d0a4\",\n        \"metadata\": {\n            \"filename\": \"Bank Good Credit Loan.pptx\",\n            \"file_directory\": \"tmpdocs\",\n            \"last_modified\": \"2023-11-02T15:16:14\",\n            \"filetype\": \"application/vnd.openxmlformats-officedocument.presentationml.presentation\",\n            \"parent_id\": \"ed83647ab77addbea9e4dca5f7d8f216\",\n            \"category_depth\": 1,\n            \"languages\": [\n                \"eng\"\n            ],\n            \"page_number\": 4\n        },\n        \"text\": \"\\u00a9 DataMites\\u2122. All Rights Reserved | www.datamites.com\"\n    },\n    {\n        \"type\": \"Title\",\n        \"element_id\": \"7207da66fd1c6771ee1a5705dc41c0c7\",\n        \"metadata\": {\n            \"filename\": \"Bank Good Credit Loan.pptx\",\n            \"file_directory\": \"tmpdocs\",\n            \"last_modified\": \"2023-11-02T15:16:14\",\n            \"filetype\": \"application/vnd.openxmlformats-officedocument.presentationml.presentation\",\n            \"category_depth\": 0,\n            \"languages\": [\n                \"eng\"\n            ],\n            \"page_number\": 5\n        },\n        \"text\": \"Explain Coding / outcomes \"\n    },\n    {\n        \"type\": \"ListItem\",\n        \"element_id\": \"815ef1753a8bcb1ce21d59819bdc6834\",\n        \"metadata\": {\n            \"filename\": \"Bank Good Credit Loan.pptx\",\n            \"file_directory\": \"tmpdocs\",\n            \"last_modified\": \"2023-11-02T15:16:14\",\n            \"filetype\": \"application/vnd.openxmlformats-officedocument.presentationml.presentation\",\n            \"parent_id\": \"7207da66fd1c6771ee1a5705dc41c0c7\",\n            \"category_depth\": 1,\n            \"languages\": [\n                \"eng\"\n            ],\n            \"page_number\": 5\n        },\n        \"text\": \"Show using Jupyter\"\n    },\n    {\n        \"type\": \"Title\",\n        \"element_id\": \"b952b3e6d0e34020f1f48b5d9243d0a4\",\n        \"metadata\": {\n            \"filename\": \"Bank Good Credit Loan.pptx\",\n            \"file_directory\": \"tmpdocs\",\n            \"last_modified\": \"2023-11-02T15:16:14\",\n            \"filetype\": \"application/vnd.openxmlformats-officedocument.presentationml.presentation\",\n            \"parent_id\": \"7207da66fd1c6771ee1a5705dc41c0c7\",\n            \"category_depth\": 1,\n            \"languages\": [\n                \"eng\"\n            ],\n            \"page_number\": 5\n        },\n        \"text\": \"\\u00a9 DataMites\\u2122. All Rights Reserved | www.datamites.com\"\n    },\n    {\n        \"type\": \"Title\",\n        \"element_id\": \"2034ce6155036f8a009ef33985209e88\",\n        \"metadata\": {\n            \"filename\": \"Bank Good Credit Loan.pptx\",\n            \"file_directory\": \"tmpdocs\",\n            \"last_modified\": \"2023-11-02T15:16:14\",\n            \"filetype\": \"application/vnd.openxmlformats-officedocument.presentationml.presentation\",\n            \"parent_id\": \"7207da66fd1c6771ee1a5705dc41c0c7\",\n            \"category_depth\": 1,\n            \"languages\": [\n                \"eng\"\n            ],\n            \"page_number\": 6\n        },\n        \"text\": \"Thank You\"\n    },\n    {\n        \"type\": \"Title\",\n        \"element_id\": \"b952b3e6d0e34020f1f48b5d9243d0a4\",\n        \"metadata\": {\n            \"filename\": \"Bank Good Credit Loan.pptx\",\n            \"file_directory\": \"tmpdocs\",\n            \"last_modified\": \"2023-11-02T15:16:14\",\n            \"filetype\": \"application/vnd.openxmlformats-officedocument.presentationml.presentation\",\n            \"parent_id\": \"7207da66fd1c6771ee1a5705dc41c0c7\",\n            \"category_depth\": 1,\n            \"languages\": [\n                \"eng\"\n            ],\n            \"page_number\": 6\n        },\n        \"text\": \"\\u00a9 DataMites\\u2122. All Rights Reserved | www.datamites.com\"\n    }\n]",
      "source_file": "Bank Good Credit Loan.pptx.json",
      "source_page": 0,
      "keywords": [
        "SQL",
        "IABAC",
        "All",
        "Base",
        "Only",
        "Contians",
        "text"
      ],
      "created_at": "2026-06-16T11:16:00.983769",
      "metadata": {
        "element_type": "text",
        "company": "Unstructured_Demo"
      }
    }
  ]
}