{
  "schema_version": "1.0",
  "source_file": "fake-email.txt",
  "total_entries": 7,
  "entries": [
    {
      "id": "c7788f8b-e38a-4d73-9271-1c57ffdec8d0",
      "type": "general",
      "title": "MIME-Version: 1.0\nDate: Fri, 16 Dec 2022 17:04:16 ...",
      "content": "MIME-Version: 1.0\nDate: Fri, 16 Dec 2022 17:04:16 -0500\nMessage-ID: <CADc-_xaLB2FeVQ7mNsoX+NJb_7hAJhBKa_zet-rtgPGenj0uVw@mail.gmail.com>\nSubject: Test Email\nFrom: Matthew Robinson <mrobinson@unstructured.io>\nTo: Matthew Robinson <mrobinson@unstructured.io>\nContent-Type: multipart/alternative; boundary=\"00000000000095c9b205eff92630\"",
      "source_file": "fake-email.txt",
      "source_page": 0,
      "keywords": [
        "MIME",
        "Date",
        "Fri",
        "Message"
      ],
      "created_at": "2026-06-16T14:12:24.614649",
      "metadata": {
        "element_type": "text",
        "company": "Unassigned",
        "topic": "Email",
        "source": "fake-email.txt"
      }
    },
    {
      "id": "8ad6ac6d-e62e-40f0-ac85-06124156c88b",
      "type": "general",
      "title": "--00000000000095c9b205eff92630\nContent-Type: text/...",
      "content": "--00000000000095c9b205eff92630\nContent-Type: text/plain; charset=\"UTF-8\"",
      "source_file": "fake-email.txt",
      "source_page": 0,
      "keywords": [
        "UTF",
        "Content",
        "text"
      ],
      "created_at": "2026-06-16T14:12:24.614739",
      "metadata": {
        "element_type": "text",
        "company": "Unassigned",
        "topic": "Email",
        "source": "fake-email.txt"
      }
    },
    {
      "id": "73bfddc2-6f5a-4dff-8e9b-174c95169290",
      "type": "general",
      "title": "This is a test email to use for unit tests.",
      "content": "This is a test email to use for unit tests.",
      "source_file": "fake-email.txt",
      "source_page": 0,
      "keywords": [],
      "created_at": "2026-06-16T14:12:24.614787",
      "metadata": {
        "element_type": "text",
        "company": "Unassigned",
        "topic": "Email",
        "source": "fake-email.txt"
      }
    },
    {
      "id": "f7e174ca-6f4b-433d-9957-2fee4d304c74",
      "type": "general",
      "title": "- Roses are red\n   - Violets are blue\n   -",
      "content": "- Roses are red\n   - Violets are blue\n   -",
      "source_file": "fake-email.txt",
      "source_page": 0,
      "keywords": [],
      "created_at": "2026-06-16T14:12:24.614824",
      "metadata": {
        "element_type": "text",
        "company": "Unassigned",
        "topic": "Email",
        "source": "fake-email.txt"
      }
    },
    {
      "id": "998e8b13-e2d1-49ca-b679-655f1478dbb8",
      "type": "general",
      "title": "--00000000000095c9b205eff92630\nContent-Type: text/...",
      "content": "--00000000000095c9b205eff92630\nContent-Type: text/html; charset=\"UTF-8\"",
      "source_file": "fake-email.txt",
      "source_page": 0,
      "keywords": [
        "UTF",
        "Content",
        "text"
      ],
      "created_at": "2026-06-16T14:12:24.614868",
      "metadata": {
        "element_type": "text",
        "company": "Unassigned",
        "topic": "Email",
        "source": "fake-email.txt"
      }
    },
    {
      "id": "97c04700-15db-4f26-a109-f0902b9e4121",
      "type": "general",
      "title": "<div dir=\"ltr\"><div>This is a test email to use fo...",
      "content": "<div dir=\"ltr\"><div>This is a test email to use for unit tests.</div><div><br></div><div>Important points:</div><div><ul><li>Roses are red</li><li>Violets are blue</li></ul></div></div>",
      "source_file": "fake-email.txt",
      "source_page": 0,
      "keywords": [],
      "created_at": "2026-06-16T14:12:24.614969",
      "metadata": {
        "element_type": "text",
        "company": "Unassigned",
        "topic": "Email",
        "source": "fake-email.txt"
      }
    },
    {
      "id": "3b854f8b-9947-4a02-bdf0-d690fc8dbc82",
      "type": "general",
      "title": "--00000000000095c9b205eff92630--",
      "content": "--00000000000095c9b205eff92630--",
      "source_file": "fake-email.txt",
      "source_page": 0,
      "keywords": [],
      "created_at": "2026-06-16T14:12:24.614998",
      "metadata": {
        "element_type": "text",
        "company": "Unassigned",
        "topic": "Email",
        "source": "fake-email.txt"
      }
    }
  ]
}